conclib/__init__.py
conclib/config.py
conclib/constants.py
conclib/errors.py
conclib/proxy/__init__.py
conclib/proxy/actor.py
conclib/proxy/client.py
conclib/proxy/envelope.py
conclib/proxy/messages.py
conclib/pykka_extensions/__init__.py
conclib/pykka_extensions/actor.py
conclib/pykka_extensions/periodicactor.py
conclib/pykka_extensions/ticker.py
conclib/utils/__init__.py
conclib/utils/apid/apid.py
conclib/utils/apid/example_api.py
conclib/utils/redisd/__init__.py
conclib/utils/redisd/redisclient.py
conclib/utils/redisd/redisserverd.py
conclib-0.0.9.dist-info/LICENSE
conclib-0.0.9.dist-info/WHEEL
conclib-0.0.9.dist-info/METADATA
conclib-0.0.9.dist-info/RECORD
