Metadata-Version: 2.1
Name: conclib
Version: 0.0.9
Summary: Python concurrency library extending Pykka.
Author-email: Armand McQueen <armandmcqueen@gmail.com>
Requires-Python: >=3.10
Classifier: License :: OSI Approved :: MIT License
Requires-Dist: pykka == 4.0.1
Requires-Dist: redis ~= 5.0.1
Requires-Dist: pydantic ~= 2.5.2
Requires-Dist: requests
Requires-Dist: ruff ~= 0.1.6 ; extra == "dev"
Requires-Dist: flit ~= 3.9.0 ; extra == "dev"
Requires-Dist: fastapi == 0.105.0 ; extra == "dev"
Requires-Dist: uvicorn[all] ~= 0.24.0.post1 ; extra == "dev"
Project-URL: Home, https://github.com/armandmcqueen/conclib
Provides-Extra: dev
